{"rabbit_version":"3.8.0","users":[{"name":"metricsGenerator","password_hash":"QPDIFWMiq/VUuBbndb/HVFlIvJ6UOU7vlfIs/vUcOQRnNDf8","hashing_algorithm":"rabbit_password_hashing_sha256","tags":"administrator"}],"vhosts":[{"name":"/"}],"permissions":[{"user":"metricsGenerator","vhost":"/","configure":".*","write":".*","read":".*"}],"topic_permissions":[],"parameters":[],"global_parameters":[{"name":"cluster_name","value":"rabbit@DESKTOP-GIEHRRD"}],"policies":[],"queues":[{"name":"queue.metrics.work","vhost":"/","durable":true,"auto_delete":false,"arguments":{"x-dead-letter-exchange":"x.metrics.dead","x-queue-type":"classic"}},{"name":"queue.metrics.dead","vhost":"/","durable":true,"auto_delete":false,"arguments":{"x-queue-type":"classic"}}],"exchanges":[{"name":"x.metrics.dead","vhost":"/","type":"direct","durable":true,"auto_delete":false,"internal":false,"arguments":{}},{"name":"x.metrics.work","vhost":"/","type":"direct","durable":true,"auto_delete":false,"internal":false,"arguments":{}}],"bindings":[{"source":"x.metrics.dead","vhost":"/","destination":"queue.metrics.dead","destination_type":"queue","routing_key":"routing.metrics.work","arguments":{}},{"source":"x.metrics.work","vhost":"/","destination":"queue.metrics.work","destination_type":"queue","routing_key":"routing.metrics.work","arguments":{}}]}